muscad/__init__.py
muscad/base.py
muscad/color.py
muscad/helpers.py
muscad/part.py
muscad/point.py
muscad/primitives.py
muscad/transformations.py
muscad/utils/__init__.py
muscad/utils/fillet.py
muscad/utils/shapes.py
muscad/utils/stack.py
muscad/utils/surface.py
muscad/utils/volume.py
muscad/vitamins/__init__.py
muscad/vitamins/bearings.py
muscad/vitamins/belts.py
muscad/vitamins/boards.py
muscad/vitamins/bolts.py
muscad/vitamins/brackets.py
muscad/vitamins/endstops.py
muscad/vitamins/extruders.py
muscad/vitamins/extrusions.py
muscad/vitamins/fans.py
muscad/vitamins/gears.py
muscad/vitamins/pulleys.py
muscad/vitamins/rods.py
muscad/vitamins/steppers.py
muscad-0.5.1.dist-info/LICENSE.txt
muscad-0.5.1.dist-info/WHEEL
muscad-0.5.1.dist-info/METADATA
muscad-0.5.1.dist-info/RECORD
