Metadata-Version: 2.1
Name: muscad
Version: 0.5.1
Summary: OpenSCAD, with a Python Spice
Home-page: https://gitlab.com/guillp/muscad
Author: Guillaume Pujol
Author-email: guillp.linux@gmail.com
Requires-Python: >=3.6,<4.0
Classifier: Programming Language :: Python :: 3
Classifier: Programming Language :: Python :: 3.6
Classifier: Programming Language :: Python :: 3.7
Classifier: Programming Language :: Python :: 3.8
Classifier: Programming Language :: Python :: 3.9
Project-URL: Repository, https://gitlab.com/guillp/muscad
